{"__symbolic":"module","version":1,"metadata":{"MoonPhasesComponent":{"__symbolic":"class","decorators":[{"__symbolic":"call","expression":{"__symbolic":"reference","module":"@angular/core","name":"Component"},"arguments":[{"selector":"moon-phases","template":"<div class=\"moon-phase-container\">\n\t<div class=\"moon-mask\"></div>\n\t<div class=\"moon-disque\"></div>\n</div>\n"}]}],"members":{"__ctor__":[{"__symbolic":"constructor","parameters":[{"__symbolic":"reference","module":"@angular/core","name":"ElementRef"}]}],"ngAfterViewInit":[{"__symbolic":"method"}],"ngOnInit":[{"__symbolic":"method"}]}}}}